{
  "generated_at": "2026-06-05T08:59:45.390542+00:00",
  "price": {
    "available": true,
    "last_close": 62816.13,
    "last_dt": "2026-06-05T08:15:00+00:00",
    "ret_24h": -0.010520288576649328,
    "ret_7d": -0.14869427242756883,
    "ret_30d": -0.22991136447223248,
    "ret_90d": -0.07550588705906669,
    "high_30d": 82850.0,
    "low_30d": 61126.01,
    "n_bars": 307997
  },
  "vol": {
    "available": true,
    "rv_1d_ann": 0.9020950284399692,
    "rv_1w_ann": 0.5646131341282015,
    "rv_30d_ann": 0.38086724368614283
  },
  "funding": {
    "available": true,
    "last": 9.914e-05,
    "last_dt": "2026-05-27T16:00:00.009000+00:00",
    "mean_30d": 1.6101444444444444e-05,
    "z_30d": 1.8900617483462374,
    "q05_30d": -5.51715e-05,
    "q95_30d": 8.02425e-05
  },
  "macro": {
    "available": true,
    "last_date": "2026-06-04",
    "dxy": {
      "last": 99.41000366210938,
      "z_30d": 0.5851638927535306,
      "chg_5d": 0.003938669281607909
    },
    "vix": {
      "last": 15.399999618530273,
      "z_30d": -1.1598877153775786,
      "chg_5d": -0.021601026526808953
    },
    "spx": {
      "last": 7584.31005859375,
      "z_30d": 1.3735354844190877,
      "chg_5d": 0.0027341601984312014
    }
  },
  "fg": {
    "available": true,
    "last": 12,
    "last_class": "Extreme Fear",
    "last_date": "2026-06-05",
    "chg_7d": -11,
    "chg_30d": -34
  },
  "sentiment_news": {
    "available": true,
    "last_date": "2026-05-25",
    "net_sentiment_today": -0.09122670614333064,
    "net_sentiment_7d_avg": -0.23773884056483485,
    "news_count_today": 54,
    "news_count_7d_avg": 75.14285714285714,
    "days_covered": 1504,
    "date_range": [
      "2021-01-01",
      "2026-05-25"
    ]
  },
  "data_health": {
    "ohlcv_15m_rows": 307997,
    "funding_rows": 7355,
    "macro_days": 2371,
    "fg_days": 3043,
    "news_days": 1504
  }
}